spacesnake/__init__.py
spacesnake/tests/__init__.py
spacesnake/tests/test_ipfsinterface.py
spacesnake-0.1.0.dist-info/LICENSE
spacesnake-0.1.0.dist-info/METADATA
spacesnake-0.1.0.dist-info/WHEEL
spacesnake-0.1.0.dist-info/entry_points.txt
spacesnake-0.1.0.dist-info/top_level.txt
spacesnake-0.1.0.dist-info/RECORD
