Metadata-Version: 2.1
Name: spacesnake
Version: 0.1.0
Summary: Python decentralized on IFPS
Home-page: UNKNOWN
Author: Koen van Eijk
Author-email: vaneijk.koen@gmail.com
License: MIT
Platform: UNKNOWN
Requires-Dist: click (==7.1.2)
Requires-Dist: requests (==2.25.1)
